bitgpt/__init__.py
bitgpt-0.1.0.dist-info/METADATA
bitgpt-0.1.0.dist-info/WHEEL
bitgpt-0.1.0.dist-info/RECORD
