Metadata-Version: 2.1
Name: bitgpt
Version: 0.1.0
Summary: 1 bit gpt
Author: Refik Can MALLI
Author-email: refikcanmalli@gmail.com
Requires-Python: >=3.11,<4.0
Classifier: Programming Language :: Python :: 3
Classifier: Programming Language :: Python :: 3.11
Classifier: Programming Language :: Python :: 3.12
